{
    "version": 164,
    "timestamp": "2022-01-21T19:23:42.483194",
    "client_patch_url": "https://lol.secure.dyn.riotcdn.net/channels/public/releases/688E6FC1C01ADE73.manifest",
    "game_patch_url": "https://lol.secure.dyn.riotcdn.net/channels/public/releases/BAA127646F53294E.manifest",
    "toggles": {
        "new_client_patcher": 100.0,
        "new_game_patcher": 100.0
    },
    "client_app_patch_url": "https://lol.secure.dyn.riotcdn.net/channels/public/releases/E617969D91ECA52C.manifest"
}