{
    "version": 583,
    "timestamp": "2021-03-23T19:01:12.402973",
    "client_patch_url": "https://lol.secure.dyn.riotcdn.net/channels/public/releases/37C54667ADAEB582.manifest",
    "game_patch_url": "https://lol.secure.dyn.riotcdn.net/channels/public/releases/4E83436510196E3F.manifest",
    "toggles": {
        "new_client_patcher": 100.0,
        "new_game_patcher": 100.0
    },
    "client_app_patch_url": "https://lol.secure.dyn.riotcdn.net/channels/public/releases/48188908F92DC772.manifest"
}